PlutoAuth/__init__.py
PlutoAuth-1.0.2.dist-info/LICENSE
PlutoAuth-1.0.2.dist-info/METADATA
PlutoAuth-1.0.2.dist-info/WHEEL
PlutoAuth-1.0.2.dist-info/top_level.txt
PlutoAuth-1.0.2.dist-info/RECORD
